micro_api_ext/__init__.py
micro_api_ext/api.py
micro_api_ext/http_exceptions.py
micro_api_ext/namespace.py
micro_api_ext/parameters.py
micro_api_ext/webargs_parser.py
micro_api_ext-1.0.0.dist-info/METADATA
micro_api_ext-1.0.0.dist-info/WHEEL
micro_api_ext-1.0.0.dist-info/top_level.txt
micro_api_ext-1.0.0.dist-info/RECORD
