Metadata-Version: 2.1
Name: micro-api-ext
Version: 1.0.0
Summary: micro_api_ext
Home-page: https://github.com/alhazmy13/api_ext
Author: Alhazmy13
Author-email: me@alhazmy13.net
License: MIT
Platform: UNKNOWN
Requires-Dist: micro-restplus-ext
Requires-Dist: flask
Requires-Dist: sqlalchemy
Requires-Dist: six
